pykuwahara/__init__.py
pykuwahara/kuwahara.py
pykuwahara-0.3.2.dist-info/LICENSE
pykuwahara-0.3.2.dist-info/METADATA
pykuwahara-0.3.2.dist-info/WHEEL
pykuwahara-0.3.2.dist-info/top_level.txt
pykuwahara-0.3.2.dist-info/RECORD
